fsx/__init__.py
fsx/_scandir_module.py
fsx/ftplib.py
fsx/glob.py
fsx/os.py
fsx/scandir.py
fsx/shutil.py
fsx/tempfile.py
fsx/zipfile.py
fsx/fstree/_DirNode.py
fsx/fstree/_FileNode.py
fsx/fstree/_FsTree.py
fsx/fstree/_Node.py
fsx/fstree/__init__.py
fsx/fstree/_shared.py
fsx/fstree/utils.py
fsx/plugins/__init__.py
fsx/plugins/_plugins.py
fsx/plugins/hookspecs.py
fsx/test/_FsxFakeFsTree.py
fsx/test/_Stat.py
fsx/test/_TrackCallsMixin.py
fsx/test/__init__.py
fsx/test/_fake_builtins.py
fsx/test/_fake_ftplib.py
fsx/test/_fake_glob.py
fsx/test/_fake_os.py
fsx/test/_fake_scandir.py
fsx/test/_fake_shutil.py
fsx/test/_fake_tempfile.py
fsx/test/_fake_zipfile.py
fsx/test/_fsx_fake.py
fsx/test/_helpers.py
fsx-1.0.13.dist-info/METADATA
fsx-1.0.13.dist-info/WHEEL
fsx-1.0.13.dist-info/top_level.txt
fsx-1.0.13.dist-info/RECORD
